AssetForge/__init__.py
AssetForge/common.py
AssetForge/core.py
AssetForge/tool.py
AssetForge/util.py
assetforge-0.3.13.dist-info/licenses/LICENSE
assetforge-0.3.13.dist-info/METADATA
assetforge-0.3.13.dist-info/WHEEL
assetforge-0.3.13.dist-info/top_level.txt
assetforge-0.3.13.dist-info/RECORD
