Metadata-Version: 2.4
Name: AssetForge
Version: 0.3.13
Summary: Building Pipeline for video game assets
Author-email: Mason John Hawver <mason.hawver@gmail.com>
License: Copyright (c) 2018 The Python Packaging Authority
Project-URL: Homepage, https://github.com/MasonJohnHawver42/AssetForge
Project-URL: Issues, https://github.com/MasonJohnHawver42/AssetForge/issues
Classifier: Programming Language :: Python :: 3
Classifier: Operating System :: OS Independent
Requires-Python: >=3.9
License-File: LICENSE
Requires-Dist: graphviz>=0.20.1
Dynamic: license-file
